[{"id": 1, "text": "O(A) professor(a) foi coerente?", "helper": "Digite um valor de 0 a 10", "ref": "T", "typ": "N", "choices": "", "min_v": 0, "max_v": 10}, {"id": 2, "text": "O(A) professor(a) explicava bem?", "helper": "Digite um valor de 0 a 10", "ref": "T", "typ": "N", "choices": "", "min_v": 0, "max_v": 10}, {"id": 3, "text": "Foi f\u00e1cil passar nesta Disciplina?", "helper": "Digite um valor de 0 a 10", "ref": "S", "typ": "N", "choices": "", "min_v": 0, "max_v": 10}, {"id": 4, "text": "O qu\u00e3o importante \u00e9 essa mat\u00e9rias no curriculo do curso?", "helper": "", "ref": "S", "typ": "O", "choices": "1,2,3,4,5", "min_v": 0, "max_v": 0}]